[
  {
    "method": "CorrSteer-S",
    "task": "MMLU",
    "ser": 0.25,
    "neg": 50,
    "pos": 175
  },
  {
    "method": "CorrSteer-S",
    "task": "MMLU-Pro",
    "ser": 0.5,
    "neg": 10,
    "pos": 10
  },
  {
    "method": "CorrSteer-S",
    "task": "GSM8K",
    "ser": 0.57,
    "neg": 56,
    "pos": 42
  },
  {
    "method": "CorrSteer-S",
    "task": "BBQ-Ambig",
    "ser": 0.0,
    "neg": 0,
    "pos": 658
  },
  {
    "method": "CorrSteer-S",
    "task": "BBQ-Disambig",
    "ser": 0.16,
    "neg": 14,
    "pos": 74
  },
  {
    "method": "CorrSteer-S",
    "task": "HarmBench",
    "ser": 0.25,
    "neg": 3,
    "pos": 9
  },
  {
    "method": "CorrSteer-S",
    "task": "SimpleQA",
    "ser": 0.21,
    "neg": 1,
    "pos": 4
  },
  {
    "method": "CorrSteer-S",
    "task": "XSTest",
    "ser": 0.35,
    "neg": 3,
    "pos": 5
  },
  {
    "method": "CorrSteer-P",
    "task": "MMLU",
    "ser": 0.19,
    "neg": 131,
    "pos": 570
  },
  {
    "method": "CorrSteer-P",
    "task": "MMLU-Pro",
    "ser": 0.41,
    "neg": 30,
    "pos": 42
  },
  {
    "method": "CorrSteer-P",
    "task": "GSM8K",
    "ser": 0.59,
    "neg": 61,
    "pos": 46
  },
  {
    "method": "CorrSteer-P",
    "task": "BBQ-Ambig",
    "ser": 0.0,
    "neg": 0,
    "pos": 1589
  },
  {
    "method": "CorrSteer-P",
    "task": "BBQ-Disambig",
    "ser": 0.16,
    "neg": 59,
    "pos": 316
  },
  {
    "method": "CorrSteer-P",
    "task": "HarmBench",
    "ser": 0.09,
    "neg": 4,
    "pos": 72
  },
  {
    "method": "CorrSteer-P",
    "task": "SimpleQA",
    "ser": 0.21,
    "neg": 3,
    "pos": 7
  },
  {
    "method": "CorrSteer-P",
    "task": "XSTest",
    "ser": 0.46,
    "neg": 8,
    "pos": 9
  },
  {
    "method": "CorrSteer-A",
    "task": "MMLU",
    "ser": 0.21,
    "neg": 182,
    "pos": 697
  },
  {
    "method": "CorrSteer-A",
    "task": "MMLU-Pro",
    "ser": 0.44,
    "neg": 40,
    "pos": 51
  },
  {
    "method": "CorrSteer-A",
    "task": "GSM8K",
    "ser": 0.74,
    "neg": 326,
    "pos": 42
  },
  {
    "method": "CorrSteer-A",
    "task": "BBQ-Ambig",
    "ser": 0.09,
    "neg": 70,
    "pos": 801
  },
  {
    "method": "CorrSteer-A",
    "task": "BBQ-Disambig",
    "ser": 0.27,
    "neg": 124,
    "pos": 341
  },
  {
    "method": "CorrSteer-A",
    "task": "HarmBench",
    "ser": 0.19,
    "neg": 16,
    "pos": 70
  },
  {
    "method": "CorrSteer-A",
    "task": "SimpleQA",
    "ser": 0.37,
    "neg": 4,
    "pos": 6
  },
  {
    "method": "CorrSteer-A",
    "task": "XSTest",
    "ser": 0.51,
    "neg": 17,
    "pos": 16
  },
  {
    "method": "SPARE (MI)",
    "task": "MMLU",
    "ser": 0.2,
    "neg": 138,
    "pos": 542
  },
  {
    "method": "SPARE (MI)",
    "task": "MMLU-Pro",
    "ser": 0.43,
    "neg": 38,
    "pos": 91
  },
  {
    "method": "SPARE (MI)",
    "task": "GSM8K",
    "ser": 0.63,
    "neg": 126,
    "pos": 73
  },
  {
    "method": "SPARE (MI)",
    "task": "BBQ-Ambig",
    "ser": 0.0,
    "neg": 5,
    "pos": 1099
  },
  {
    "method": "SPARE (MI)",
    "task": "BBQ-Disambig",
    "ser": 0.17,
    "neg": 16,
    "pos": 80
  },
  {
    "method": "SPARE (MI)",
    "task": "HarmBench",
    "ser": 0.71,
    "neg": 53,
    "pos": 22
  },
  {
    "method": "SPARE (MI)",
    "task": "SimpleQA",
    "ser": 0.33,
    "neg": 6,
    "pos": 12
  },
  {
    "method": "SPARE (MI)",
    "task": "XSTest",
    "ser": 0.67,
    "neg": 20,
    "pos": 10
  },
  {
    "method": "Fine-tuning",
    "task": "MMLU",
    "ser": 0.41,
    "neg": 1108,
    "pos": 1616
  },
  {
    "method": "Fine-tuning",
    "task": "MMLU-Pro",
    "ser": 0.46,
    "neg": 357,
    "pos": 418
  },
  {
    "method": "Fine-tuning",
    "task": "GSM8K",
    "ser": 0.65,
    "neg": 213,
    "pos": 116
  },
  {
    "method": "DSG (Fisher)",
    "task": "MMLU",
    "ser": 0.42,
    "neg": 55,
    "pos": 40
  },
  {
    "method": "DSG (Fisher)",
    "task": "MMLU-Pro",
    "ser": 0.6,
    "neg": 6,
    "pos": 4
  },
  {
    "method": "DSG (Fisher)",
    "task": "GSM8K",
    "ser": 0.58,
    "neg": 29,
    "pos": 50
  },
  {
    "method": "DSG (Fisher)",
    "task": "BBQ-Ambig",
    "ser": 0.46,
    "neg": 39,
    "pos": 45
  },
  {
    "method": "DSG (Fisher)",
    "task": "BBQ-Disambig",
    "ser": 0.52,
    "neg": 21,
    "pos": 44
  },
  {
    "method": "DSG (Fisher)",
    "task": "HarmBench",
    "ser": 0.21,
    "neg": 4,
    "pos": 15
  },
  {
    "method": "DSG (Fisher)",
    "task": "SimpleQA",
    "ser": 0.52,
    "neg": 12,
    "pos": 11
  },
  {
    "method": "DSG (Fisher)",
    "task": "XSTest",
    "ser": 0.32,
    "neg": 13,
    "pos": 28
  },
  {
    "method": "CAA",
    "task": "MMLU",
    "ser": 0.27,
    "neg": 186,
    "pos": 515
  },
  {
    "method": "CAA",
    "task": "MMLU-Pro",
    "ser": 0.55,
    "neg": 42,
    "pos": 35
  },
  {
    "method": "CAA",
    "task": "GSM8K",
    "ser": 1.0,
    "neg": 722,
    "pos": 0
  },
  {
    "method": "CAA",
    "task": "BBQ-Ambig",
    "ser": 0.2,
    "neg": 214,
    "pos": 1077
  },
  {
    "method": "CAA",
    "task": "BBQ-Disambig",
    "ser": 0.62,
    "neg": 1014,
    "pos": 612
  },
  {
    "method": "CAA",
    "task": "HarmBench",
    "ser": 1.0,
    "neg": 132,
    "pos": 0
  },
  {
    "method": "CAA",
    "task": "SimpleQA",
    "ser": 0.64,
    "neg": 77,
    "pos": 43
  },
  {
    "method": "CAA",
    "task": "XSTest",
    "ser": 0.88,
    "neg": 51,
    "pos": 7
  }
]